pycity_scheduling/__init__.py
pycity_scheduling/constants.py
pycity_scheduling/exceptions.py
pycity_scheduling/solvers.py
pycity_scheduling/algorithms/__init__.py
pycity_scheduling/algorithms/algorithm.py
pycity_scheduling/algorithms/algorithm_ray.py
pycity_scheduling/algorithms/central_optimization_algorithm.py
pycity_scheduling/algorithms/derivative_free_aladin_algorithm.py
pycity_scheduling/algorithms/derivative_free_aladin_algorithm_ray.py
pycity_scheduling/algorithms/derivative_free_aladin_algorithm_ray_Hvet.py
pycity_scheduling/algorithms/dual_decomposition_algorithm.py
pycity_scheduling/algorithms/dual_decomposition_algorithm_mpi.py
pycity_scheduling/algorithms/dual_decomposition_algorithm_ray.py
pycity_scheduling/algorithms/exchange_admm_algorithm.py
pycity_scheduling/algorithms/exchange_admm_algorithm_mpi.py
pycity_scheduling/algorithms/exchange_admm_algorithm_ray.py
pycity_scheduling/algorithms/exchange_miqp_admm_algorithm.py
pycity_scheduling/algorithms/exchange_miqp_admm_algorithm_mpi.py
pycity_scheduling/algorithms/exchange_miqp_admm_algorithm_ray.py
pycity_scheduling/algorithms/local_optimization_algorithm.py
pycity_scheduling/algorithms/stand_alone_optimization_algorithm.py
pycity_scheduling/case_studies/__init__.py
pycity_scheduling/case_studies/p4elecs_exercises/exercise1.ipynb
pycity_scheduling/case_studies/p4elecs_exercises/exercise2.ipynb
pycity_scheduling/case_studies/software_x_pycity-scheduling/illustrative_code_example_cost_minimization_use_case_interactive.ipynb
pycity_scheduling/classes/__init__.py
pycity_scheduling/classes/apartment.py
pycity_scheduling/classes/battery.py
pycity_scheduling/classes/boiler.py
pycity_scheduling/classes/building.py
pycity_scheduling/classes/building_energy_system.py
pycity_scheduling/classes/chiller.py
pycity_scheduling/classes/city_district.py
pycity_scheduling/classes/combined_heat_power.py
pycity_scheduling/classes/curtailable_load.py
pycity_scheduling/classes/deferrable_load.py
pycity_scheduling-1.4.2.dist-info/licenses/LICENSE.txt
pycity_scheduling-1.4.2.dist-info/METADATA
pycity_scheduling-1.4.2.dist-info/WHEEL
pycity_scheduling-1.4.2.dist-info/top_level.txt
pycity_scheduling-1.4.2.dist-info/RECORD
