Metadata-Version: 2.4
Name: pycity_scheduling
Version: 1.4.2
Summary: A Python framework for the development, testing, and assessment of optimization-basedpower scheduling algorithms for multi-energy systems in city districts
Home-page: https://git.rwth-aachen.de/acs/public/simulation/pycity_scheduling
Author: Institute for Automation of Complex Power Systems (ACS),E.ON Energy Research Center (E.ON ERC),RWTH Aachen University
Author-email: post_acs@eonerc.rwth-aachen.de
License: MIT
Platform: any
Classifier: Development Status :: 5 - Production/Stable
Classifier: Operating System :: OS Independent
Classifier: Intended Audience :: Science/Research
Classifier: License :: OSI Approved :: MIT License
Classifier: Topic :: Scientific/Engineering
Classifier: Natural Language :: English
Classifier: Programming Language :: Python :: 3.9
Classifier: Programming Language :: Python :: 3.10
Classifier: Programming Language :: Python :: 3.11
Classifier: Programming Language :: Python :: 3.12
Requires-Python: >=3.9
License-File: LICENSE.txt
Requires-Dist: numpy==1.26.0
Requires-Dist: pandas==2.1.1
Requires-Dist: matplotlib==3.8.0
Requires-Dist: pyomo==6.8.2
Requires-Dist: gurobipy==12.0.0
Requires-Dist: pycity_base==0.3.3
Requires-Dist: scikit-learn==1.3.2
Requires-Dist: psutil==6.1.0
Requires-Dist: pyarrow==17.0.0
Requires-Dist: ray==2.40.0
Provides-Extra: mpi
Requires-Dist: mpi4py==4.0.0; extra == "mpi"
Provides-Extra: test
Requires-Dist: pytest==7.4.2; extra == "test"
Dynamic: author
Dynamic: author-email
Dynamic: classifier
Dynamic: description
Dynamic: description-content-type
Dynamic: home-page
Dynamic: license
Dynamic: license-file
Dynamic: platform
Dynamic: provides-extra
Dynamic: requires-dist
Dynamic: requires-python
Dynamic: summary
